{
  "RESOLVED_ENTITIES": {
    "Juventino Mejia-Orosco": "Juventino Mejia-Orosco",
    "CLARK": "CLARK",
    "Juventino": "Juventino Mejia-Orosco",
    "Mejia-Orosco": "Juventino Mejia-Orosco",
    "Hector Galvencio Paz-Ortega": "Hector Galvencio Paz-Ortega",
    "Carlos Enrique Cruz-Morales": "Carlos Enrique Cruz-Morales",
    "the defendant": "Juventino Mejia-Orosco",
    "the district court": null,
    "the Chief Judge": "CLARK",
    "Paz-Ortega": "Hector Galvencio Paz-Ortega",
    "Cruz-Morales": "Carlos Enrique Cruz-Morales",
    "the aliens": null,
    "relatives of the aliens": null,
    "family members": null,
    "immigration officials": null,
    "law enforcement officials": null,
    "the court of appeals": null,
    "the witnesses": null,
    "the offender": "Juventino Mejia-Orosco",
    "prisoners": null,
    "parole officials": null,
    "Senator Edward M. Kennedy": "Edward M. Kennedy",
    "Edward M. Kennedy": "Edward M. Kennedy",
    "the senator": "Edward M. Kennedy",
    "Congress": null,
    "district judges": null,
    "offenders": null,
    "victims": null,
    "society": null,
    "the sentencing judge": null,
    "an individual offender": "Juventino Mejia-Orosco",
    "the court": null,
    "government officials": null,
    "the Sentencing Commission": null,
    "an organizer": null,
    "a leader": null,
    "a manager": null,
    "a supervisor": null,
    "the government": null,
    "participants": null,
    "the trial judge": null,
    "the Court": null,
    "the judge": null,
    "the jury": null,
    "the sentencing commission": null,
    "district courts": null
  },
  "AUXILIARY_DESCRIPTIONS": {
    "Juventino Mejia-Orosco": "defendant convicted of illegally transporting aliens into the United States, smuggler, sentenced to 10 months in prison and fined $4,000, pled guilty to one count of illegally transporting an alien, previously convicted of unlawful entry, potentially considered an organizer or leader in a criminal activity, found by the district court to be 'an organizer, leader, manager, or supervisor', status as a \"manager\" is a question of fact for the jury",
    "CLARK": "Chief Judge presiding over the case",
    "Hector Galvencio Paz-Ortega": "passenger and citizen of Guatemala, related to Juventino Mejia-Orosco, alien being smuggled",
    "Carlos Enrique Cruz-Morales": "passenger and citizen of Guatemala, related to Juventino Mejia-Orosco, alien being smuggled",
    "Edward M. Kennedy": "Described the sentencing guidelines as a comprehensive approach to reduce disparity in punishment and ensure fair sentences for offenders, victims, and society"
  }
}