{
  "RESOLVED_ENTITIES": {
    "the highway": "Interstate Highway 35",
    "the border": "United States-Mexican border",
    "U.S.-Mexico border": "United States-Mexico border"
  },
  "AUXILIARY_DESCRIPTIONS": {
    "United States-Mexico border": "geographical boundary relevant to the case and location of the incident, reference point for distance",
    "Interstate Highway 35": "highway leading directly to the border and passing through Laredo, Texas, common smuggling route with history of alien smuggling, where vehicles are usually traveling at higher speeds late at night"
  }
}