{
  "RESOLVED_ENTITIES": {
    "United States": "United States",
    "this appeal": null,
    "the district": null,
    "her vehicle": null,
    "the jury": null,
    "Moore, Texas": "Moore, Texas",
    "Interstate Highway 35": "Interstate Highway 35",
    "Mexican border": "United States-Mexican border",
    "the northbound lanes": "northbound lanes of Interstate Highway 35",
    "their marked border patrol sedan": null,
    "the camper": null,
    "the bumper": null,
    "the tires": null,
    "the wheel wells": null,
    "the rear": null,
    "the vehicle": null,
    "the window": null,
    "the truck": null,
    "the front end": null,
    "the cab": null,
    "the back seat": null,
    "the brush": null,
    "the rear window": null,
    "the floor": null,
    "the district court": null,
    "the camper compartment": null,
    "border": "United States-Mexican border",
    "the area": null,
    "the border": "United States-Mexican border",
    "the country": "United States",
    "United States-Mexican border": "United States-Mexican border",
    "Laredo, Texas": "Laredo, Texas",
    "Interstate 35": "Interstate Highway 35",
    "the city": "Laredo, Texas",
    "this country": "United States",
    "the towns": null,
    "Brignoni-Ponce": "Brignoni-Ponce standard"
  },
  "AUXILIARY_DESCRIPTIONS": {
    "United States": "country where the federal district court is located",
    "Moore, Texas": "location where the incident occurred, approximately 115 miles from the United States-Mexican border",
    "Interstate Highway 35": "highway where the incident took place, with northbound lanes, leading directly to the United States-Mexican border and passing through Laredo, Texas",
    "Mexican border": "geographical reference point, approximately 115 miles from Moore, Texas, relevant for roving border patrol stops",
    "United States-Mexican border": "geographical reference point relevant for roving border patrol stops and the Brignoni-Ponce test",
    "Laredo, Texas": "location through which Interstate 35 passes, one of the towns before reaching Moore",
    "Brignoni-Ponce standard": "a standard for reasonably warranting suspicion in border patrol stops"
  }
}